pydatavec/__init__.py
pydatavec/conditions.py
pydatavec/java_classes.py
pydatavec/schema.py
pydatavec/transform_process.py
pydatavec/utils.py
pydatavec/executors/__init__.py
pydatavec/executors/local.py
pydatavec/executors/spark.py
pydatavec-0.1.2.dist-info/DESCRIPTION.rst
pydatavec-0.1.2.dist-info/METADATA
pydatavec-0.1.2.dist-info/RECORD
pydatavec-0.1.2.dist-info/WHEEL
pydatavec-0.1.2.dist-info/metadata.json
pydatavec-0.1.2.dist-info/top_level.txt
